torchdriveenv/__init__.py
torchdriveenv/env_utils.py
torchdriveenv/gym_env.py
torchdriveenv/helpers.py
torchdriveenv/iai.py
torchdriveenv/data/training_cases.yml
torchdriveenv/data/validation_cases.yml
torchdriveenv/resources/background_traffic/carla_Town01_10_634.json
torchdriveenv/resources/background_traffic/carla_Town01_15_15.json
torchdriveenv/resources/background_traffic/carla_Town01_15_575.json
torchdriveenv/resources/background_traffic/carla_Town01_15_673.json
torchdriveenv/resources/background_traffic/carla_Town01_15_770.json
torchdriveenv/resources/background_traffic/carla_Town01_18_22.json
torchdriveenv/resources/background_traffic/carla_Town01_18_268.json
torchdriveenv/resources/background_traffic/carla_Town01_18_654.json
torchdriveenv/resources/background_traffic/carla_Town01_5_306.json
torchdriveenv/resources/background_traffic/carla_Town01_5_57.json
torchdriveenv/resources/background_traffic/carla_Town02_10_131.json
torchdriveenv/resources/background_traffic/carla_Town02_15_142.json
torchdriveenv/resources/background_traffic/carla_Town02_15_270.json
torchdriveenv/resources/background_traffic/carla_Town02_15_342.json
torchdriveenv/resources/background_traffic/carla_Town02_15_568.json
torchdriveenv/resources/background_traffic/carla_Town02_15_795.json
torchdriveenv/resources/background_traffic/carla_Town02_15_9.json
torchdriveenv/resources/background_traffic/carla_Town02_15_920.json
torchdriveenv/resources/background_traffic/carla_Town02_18_141.json
torchdriveenv/resources/background_traffic/carla_Town02_18_229.json
torchdriveenv/resources/background_traffic/carla_Town02_18_345.json
torchdriveenv/resources/background_traffic/carla_Town02_18_356.json
torchdriveenv/resources/background_traffic/carla_Town02_18_501.json
torchdriveenv/resources/background_traffic/carla_Town02_18_515.json
torchdriveenv/resources/background_traffic/carla_Town02_18_682.json
torchdriveenv/resources/background_traffic/carla_Town02_18_746.json
torchdriveenv-0.1.1.dist-info/METADATA
torchdriveenv-0.1.1.dist-info/WHEEL
torchdriveenv-0.1.1.dist-info/top_level.txt
torchdriveenv-0.1.1.dist-info/RECORD
